LICENSE
MANIFEST.in
README.rst
SAGA_optimize.py
requirements.txt
setup.py
SAGA_optimize.egg-info/PKG-INFO
SAGA_optimize.egg-info/SAGA_optimize.py
SAGA_optimize.egg-info/SOURCES.txt
SAGA_optimize.egg-info/dependency_links.txt
SAGA_optimize.egg-info/requires.txt
SAGA_optimize.egg-info/top_level.txt
doc/Makefile
doc/api.rst
doc/conf.py
doc/guide.rst
doc/index.rst
doc/tutorial.rst
doc/_build/html/_sources/api.rst.txt
doc/_build/html/_sources/guide.rst.txt
doc/_build/html/_sources/index.rst.txt
doc/_build/html/_sources/tutorial.rst.txt