Metadata-Version: 1.1
Name: SAGA-optimize
Version: 1.0.3.3
Summary: Optimization method for solving boundary-value inverse problem based on a combined simulated annealing and genetic algorithm
Home-page: https://github.com/MoseleyBioinformaticsLab/SAGA_optimize.git
Author: Huan Jin
Author-email: hji236@g.uky.edu
License: BSD
Keywords: optimization inverse problem simulated annealing genetic algorithm
Platform: any
Classifier: Development Status :: 4 - Beta
Classifier: Environment :: Console
Classifier: Intended Audience :: Developers
Classifier: Intended Audience :: Science/Research
Classifier: License :: OSI Approved :: BSD License
Classifier: Operating System :: OS Independent
Classifier: Programming Language :: Python :: 3.4
Classifier: Programming Language :: Python :: 3.5
Classifier: Programming Language :: Python :: 3.6
Classifier: Programming Language :: Python :: 3.7
